<?xml version="1.0" encoding="utf-8" ?>
<dwsync>
<file name="check_session.php" server="prattbuild.ca/pratttrade/" local="129885621631603134" remote="129885586800000000" />
<file name="head_text.php" server="prattbuild.ca/pratttrade/" local="129772828775437111" remote="129772720800000000" />
<file name="index.php" server="prattbuild.ca/pratttrade/" local="129772828775437111" remote="129772720800000000" />
<file name="index_logic.php" server="prattbuild.ca/pratttrade/" local="129885627568094068" remote="129885586800000000" />
<file name="initialize_logic.php" server="prattbuild.ca/pratttrade/" local="129772828775537111" remote="129772720800000000" />
<file name="leftSideBar.php" server="prattbuild.ca/pratttrade/" local="129885624517687543" remote="129885586800000000" />
<file name="login_screen.php" server="prattbuild.ca/pratttrade/" local="129774574031783478" remote="129776700600000000" />
<file name="lot_aps_details_page.php" server="prattbuild.ca/pratttrade/" local="129885626320594571" remote="129885586800000000" />
<file name="site_link_bar.php" server="prattbuild.ca/pratttrade/" local="129772828775637111" remote="129772720800000000" />
<file name="site_lots_page.php" server="prattbuild.ca/pratttrade/" local="129772856863816404" remote="129772748400000000" />
<file name="table_aps_header.php" server="prattbuild.ca/pratttrade/" local="129772839421138659" remote="129772731000000000" />
<file name="table_offer_amendments.php" server="prattbuild.ca/pratttrade/" local="129772828775737112" remote="129772720800000000" />
<file name="table_offer_change_orders.php" server="prattbuild.ca/pratttrade/" local="129772828775737112" remote="129772720800000000" />
<file name="table_offer_extras.php" server="prattbuild.ca/pratttrade/" local="129772828775737112" remote="129772720800000000" />
<file name="table_offer_work_credits.php" server="prattbuild.ca/pratttrade/" local="129772828775837112" remote="129772720800000000" />
<file name="uploaded_documents.php" server="prattbuild.ca/pratttrade/" local="129776808874844342" remote="129776700600000000" />
<file name="vars.php" server="prattbuild.ca/pratttrade/" local="129772828775837112" remote="129772720800000000" />
<file name="lot_colour_chart_print.php" server="prattbuild.ca/pratttrade/" local="129885697700269413" remote="129885589200000000" />
</dwsync>